sushengjie/__init__.py
sushengjie/core.py
sushengjie-0.0.2.dist-info/licenses/LICENSE
sushengjie-0.0.2.dist-info/METADATA
sushengjie-0.0.2.dist-info/WHEEL
sushengjie-0.0.2.dist-info/top_level.txt
sushengjie-0.0.2.dist-info/RECORD
